LICENSE
MANIFEST.in
README.rst
setup.cfg
setup.py
django_rest_messaging.egg-info/PKG-INFO
django_rest_messaging.egg-info/SOURCES.txt
django_rest_messaging.egg-info/dependency_links.txt
django_rest_messaging.egg-info/requires.txt
django_rest_messaging.egg-info/top_level.txt
rest_messaging/__init__.py
rest_messaging/apps.py
rest_messaging/compat.py
rest_messaging/middleware.py
rest_messaging/models.py
rest_messaging/pagination.py
rest_messaging/permissions.py
rest_messaging/serializers.py
rest_messaging/signals.py
rest_messaging/urls.py
rest_messaging/views.py
rest_messaging/migrations/0001_initial.py
rest_messaging/migrations/__init__.py